ldj
