Metadata-Version: 2.1
Name: ldj-common
Version: 0.0.5
Summary: LDJ公共库(aop/crypto/json/nacos/oss/kafka)
Home-page: https://www.messagesea.com/
Author: ldj
Author-email: zuiwoxing@qq.com
License: UNKNOWN
Platform: UNKNOWN
Classifier: Development Status :: 3 - Alpha
Classifier: Intended Audience :: Developers
Classifier: Topic :: Software Development :: Build Tools
Classifier: License :: OSI Approved :: MIT License
Classifier: Programming Language :: Python :: 3.8
